fox_proxy_kit/__init__.py
fox_proxy_kit/api_services.py
fox_proxy_kit/config.py
fox_proxy_kit/format.py
fox_proxy_kit/info.py
fox_proxy_kit/parser.py
fox_proxy_kit/proxy.py
fox_proxy_kit-0.1.7.dist-info/licenses/LICENSE
fox_proxy_kit-0.1.7.dist-info/METADATA
fox_proxy_kit-0.1.7.dist-info/WHEEL
fox_proxy_kit-0.1.7.dist-info/top_level.txt
fox_proxy_kit-0.1.7.dist-info/RECORD
